[{
  "__name__": "G_1",
  "__type__": "gate",
  "_gamma_": 
      [ [ -4.624155e+00 ],
        [ 2.318403e+00 ] ],
  "children": 
    [
      {
        "__family__": "normal",
        "__name__": "E_1",
        "__type__": "expert",
        "_beta_": 
            [ -2.234756e-03, -1.037052e-02 ],
        "_par_": 
            {
              "_logsigma_sq_": 3.669019e+00
            }
      },
      {
        "__name__": "G_2",
        "__type__": "gate",
        "_gamma_": 
            [ [ -7.008290e-01 ],
              [ 5.977001e-01 ] ],
        "children": 
          [
            {
              "__family__": "normal",
              "__name__": "E_2",
              "__type__": "expert",
              "_beta_": 
                  [ -2.032125e-03, 8.182098e-03 ],
              "_par_": 
                  {
                    "_logsigma_sq_": 2.115557e+02
                  }
            },
            {
              "__name__": "G_3",
              "__type__": "gate",
              "_gamma_": 
                  [ [ -8.175973e-01 ],
                    [ 7.144400e-02 ] ],
              "children": 
                [
                  {
                    "__family__": "normal",
                    "__name__": "E_3",
                    "__type__": "expert",
                    "_beta_": 
                        [ 3.955813e-03, -1.815305e-03 ],
                    "_par_": 
                        {
                          "_logsigma_sq_": 9.519793e-01
                        }
                  },
                  {
                    "__name__": "G_4",
                    "__type__": "gate",
                    "_gamma_": 
                        [ [ 1.642650e+00 ],
                          [ 1.190806e-01 ] ],
                    "children": 
                      [
                        {
                          "__name__": "G_5",
                          "__type__": "gate",
                          "_gamma_": 
                              [ [ 9.160212e+00 ],
                                [ -2.735800e+01 ] ],
                          "children": 
                            [
                              {
                                "__family__": "normal",
                                "__name__": "E_5",
                                "__type__": "expert",
                                "_beta_": 
                                    [ 7.243380e-03, 2.856985e-03 ],
                                "_par_": 
                                    {
                                      "_logsigma_sq_": 5.947774e-02
                                    }
                              },
                              {
                                "__family__": "normal",
                                "__name__": "E_6",
                                "__type__": "expert",
                                "_beta_": 
                                    [ 5.190365e-03, 3.103967e-03 ],
                                "_par_": 
                                    {
                                      "_logsigma_sq_": 6.560129e-01
                                    }
                              }
                            ]
                        },
                        {
                          "__family__": "normal",
                          "__name__": "E_4",
                          "__type__": "expert",
                          "_beta_": 
                              [ -4.925503e-03, -1.385707e-03 ],
                          "_par_": 
                              {
                                "_logsigma_sq_": 7.815749e-01
                              }
                        }
                      ]
                  }
                ]
            }
          ]
      }
    ]
},{
  "__name__": "G_1",
  "__type__": "gate",
  "_gamma_": 
      [ [ -4.624155e+00 ],
        [ 2.318403e+00 ] ],
  "children": 
    [
      {
        "__family__": "normal",
        "__name__": "E_1",
        "__type__": "expert",
        "_beta_": 
            [ 8.102315e-03, 6.102175e-03 ],
        "_par_": 
            {
              "_logsigma_sq_": 2.071786e-01
            }
      },
      {
        "__name__": "G_2",
        "__type__": "gate",
        "_gamma_": 
            [ [ -6.041428e-01 ],
              [ -8.568941e-01 ] ],
        "children": 
          [
            {
              "__family__": "normal",
              "__name__": "E_2",
              "__type__": "expert",
              "_beta_": 
                  [ -1.253528e-02, 1.599505e-03 ],
              "_par_": 
                  {
                    "_logsigma_sq_": 6.075503e-02
                  }
            },
            {
              "__name__": "G_3",
              "__type__": "gate",
              "_gamma_": 
                  [ [ 3.222603e+00 ],
                    [ -9.086841e+00 ] ],
              "children": 
                [
                  {
                    "__family__": "normal",
                    "__name__": "E_3",
                    "__type__": "expert",
                    "_beta_": 
                        [ -3.953329e-03, -8.679250e-03 ],
                    "_par_": 
                        {
                          "_logsigma_sq_": 4.997729e-01
                        }
                  },
                  {
                    "__name__": "G_4",
                    "__type__": "gate",
                    "_gamma_": 
                        [ [ 1.642650e+00 ],
                          [ 1.190806e-01 ] ],
                    "children": 
                      [
                        {
                          "__name__": "G_5",
                          "__type__": "gate",
                          "_gamma_": 
                              [ [ 3.968938e+01 ],
                                [ 2.412036e+01 ] ],
                          "children": 
                            [
                              {
                                "__family__": "normal",
                                "__name__": "E_5",
                                "__type__": "expert",
                                "_beta_": 
                                    [ -6.134432e-03, 4.904278e-04 ],
                                "_par_": 
                                    {
                                      "_logsigma_sq_": 4.241220e-01
                                    }
                              },
                              {
                                "__family__": "normal",
                                "__name__": "E_6",
                                "__type__": "expert",
                                "_beta_": 
                                    [ -3.804590e-03, -1.059261e-02 ],
                                "_par_": 
                                    {
                                      "_logsigma_sq_": 8.389643e-01
                                    }
                              }
                            ]
                        },
                        {
                          "__family__": "normal",
                          "__name__": "E_4",
                          "__type__": "expert",
                          "_beta_": 
                              [ -4.752218e-03, 2.580647e-03 ],
                          "_par_": 
                              {
                                "_logsigma_sq_": 3.743973e-01
                              }
                        }
                      ]
                  }
                ]
            }
          ]
      }
    ]
},{
  "__name__": "G_1",
  "__type__": "gate",
  "_gamma_": 
      [ [ -4.624155e+00 ],
        [ 2.318403e+00 ] ],
  "children": 
    [
      {
        "__family__": "normal",
        "__name__": "E_1",
        "__type__": "expert",
        "_beta_": 
            [ -7.005461e-03, -1.463319e-02 ],
        "_par_": 
            {
              "_logsigma_sq_": 6.382538e+00
            }
      },
      {
        "__name__": "G_2",
        "__type__": "gate",
        "_gamma_": 
            [ [ -2.635457e+00 ],
              [ 1.539041e+00 ] ],
        "children": 
          [
            {
              "__family__": "normal",
              "__name__": "E_2",
              "__type__": "expert",
              "_beta_": 
                  [ 3.424962e-03, -2.704354e-03 ],
              "_par_": 
                  {
                    "_logsigma_sq_": 1.501391e+00
                  }
            },
            {
              "__name__": "G_3",
              "__type__": "gate",
              "_gamma_": 
                  [ [ 3.222603e+00 ],
                    [ -9.086841e+00 ] ],
              "children": 
                [
                  {
                    "__family__": "normal",
                    "__name__": "E_3",
                    "__type__": "expert",
                    "_beta_": 
                        [ 3.330061e-04, -1.741511e-03 ],
                    "_par_": 
                        {
                          "_logsigma_sq_": 3.393425e+00
                        }
                  },
                  {
                    "__name__": "G_4",
                    "__type__": "gate",
                    "_gamma_": 
                        [ [ 9.341698e-01 ],
                          [ -1.614390e+00 ] ],
                    "children": 
                      [
                        {
                          "__name__": "G_5",
                          "__type__": "gate",
                          "_gamma_": 
                              [ [ 3.968938e+01 ],
                                [ 2.412036e+01 ] ],
                          "children": 
                            [
                              {
                                "__family__": "normal",
                                "__name__": "E_5",
                                "__type__": "expert",
                                "_beta_": 
                                    [ -1.431429e-02, -3.150385e-03 ],
                                "_par_": 
                                    {
                                      "_logsigma_sq_": 1.280082e-01
                                    }
                              },
                              {
                                "__family__": "normal",
                                "__name__": "E_6",
                                "__type__": "expert",
                                "_beta_": 
                                    [ 1.363583e-02, -7.206494e-04 ],
                                "_par_": 
                                    {
                                      "_logsigma_sq_": 1.412247e-01
                                    }
                              }
                            ]
                        },
                        {
                          "__family__": "normal",
                          "__name__": "E_4",
                          "__type__": "expert",
                          "_beta_": 
                              [ -2.779143e-03, 6.827587e-03 ],
                          "_par_": 
                              {
                                "_logsigma_sq_": 1.130398e-01
                              }
                        }
                      ]
                  }
                ]
            }
          ]
      }
    ]
},{
  "__name__": "G_1",
  "__type__": "gate",
  "_gamma_": 
      [ [ -4.624155e+00 ],
        [ 2.318403e+00 ] ],
  "children": 
    [
      {
        "__family__": "normal",
        "__name__": "E_1",
        "__type__": "expert",
        "_beta_": 
            [ -9.379675e-03, 4.439047e-03 ],
        "_par_": 
            {
              "_logsigma_sq_": 1.026945e+00
            }
      },
      {
        "__name__": "G_2",
        "__type__": "gate",
        "_gamma_": 
            [ [ 1.441188e-01 ],
              [ 7.917641e-01 ] ],
        "children": 
          [
            {
              "__family__": "normal",
              "__name__": "E_2",
              "__type__": "expert",
              "_beta_": 
                  [ -2.249360e-03, 6.967488e-03 ],
              "_par_": 
                  {
                    "_logsigma_sq_": 4.664071e-01
                  }
            },
            {
              "__name__": "G_3",
              "__type__": "gate",
              "_gamma_": 
                  [ [ -2.105061e+00 ],
                    [ 3.223911e+00 ] ],
              "children": 
                [
                  {
                    "__family__": "normal",
                    "__name__": "E_3",
                    "__type__": "expert",
                    "_beta_": 
                        [ 4.496654e-03, 5.184659e-03 ],
                    "_par_": 
                        {
                          "_logsigma_sq_": 3.726395e+00
                        }
                  },
                  {
                    "__name__": "G_4",
                    "__type__": "gate",
                    "_gamma_": 
                        [ [ 9.341698e-01 ],
                          [ -1.614390e+00 ] ],
                    "children": 
                      [
                        {
                          "__name__": "G_5",
                          "__type__": "gate",
                          "_gamma_": 
                              [ [ 3.968938e+01 ],
                                [ 2.412036e+01 ] ],
                          "children": 
                            [
                              {
                                "__family__": "normal",
                                "__name__": "E_5",
                                "__type__": "expert",
                                "_beta_": 
                                    [ -6.163342e-04, 1.011675e-02 ],
                                "_par_": 
                                    {
                                      "_logsigma_sq_": 1.387743e-01
                                    }
                              },
                              {
                                "__family__": "normal",
                                "__name__": "E_6",
                                "__type__": "expert",
                                "_beta_": 
                                    [ 3.200067e-03, 1.006266e-03 ],
                                "_par_": 
                                    {
                                      "_logsigma_sq_": 4.681418e-02
                                    }
                              }
                            ]
                        },
                        {
                          "__family__": "normal",
                          "__name__": "E_4",
                          "__type__": "expert",
                          "_beta_": 
                              [ 4.900192e-03, -8.635526e-03 ],
                          "_par_": 
                              {
                                "_logsigma_sq_": 6.577329e-01
                              }
                        }
                      ]
                  }
                ]
            }
          ]
      }
    ]
},{
  "__name__": "G_1",
  "__type__": "gate",
  "_gamma_": 
      [ [ -4.624155e+00 ],
        [ 2.318403e+00 ] ],
  "children": 
    [
      {
        "__family__": "normal",
        "__name__": "E_1",
        "__type__": "expert",
        "_beta_": 
            [ -4.132333e-03, -1.118966e-02 ],
        "_par_": 
            {
              "_logsigma_sq_": 3.901889e-01
            }
      },
      {
        "__name__": "G_2",
        "__type__": "gate",
        "_gamma_": 
            [ [ 1.441188e-01 ],
              [ 7.917641e-01 ] ],
        "children": 
          [
            {
              "__family__": "normal",
              "__name__": "E_2",
              "__type__": "expert",
              "_beta_": 
                  [ -1.167690e-02, 7.627226e-03 ],
              "_par_": 
                  {
                    "_logsigma_sq_": 4.283395e-01
                  }
            },
            {
              "__name__": "G_3",
              "__type__": "gate",
              "_gamma_": 
                  [ [ -1.402009e+00 ],
                    [ 3.159036e+00 ] ],
              "children": 
                [
                  {
                    "__family__": "normal",
                    "__name__": "E_3",
                    "__type__": "expert",
                    "_beta_": 
                        [ -6.735412e-03, -5.726038e-04 ],
                    "_par_": 
                        {
                          "_logsigma_sq_": 1.632244e+00
                        }
                  },
                  {
                    "__name__": "G_4",
                    "__type__": "gate",
                    "_gamma_": 
                        [ [ 1.924702e+00 ],
                          [ 4.239958e-01 ] ],
                    "children": 
                      [
                        {
                          "__name__": "G_5",
                          "__type__": "gate",
                          "_gamma_": 
                              [ [ -3.423616e+01 ],
                                [ -3.061324e+00 ] ],
                          "children": 
                            [
                              {
                                "__family__": "normal",
                                "__name__": "E_5",
                                "__type__": "expert",
                                "_beta_": 
                                    [ 1.376624e-03, 1.500140e-03 ],
                                "_par_": 
                                    {
                                      "_logsigma_sq_": 7.685509e-02
                                    }
                              },
                              {
                                "__family__": "normal",
                                "__name__": "E_6",
                                "__type__": "expert",
                                "_beta_": 
                                    [ -5.198814e-03, -7.518919e-03 ],
                                "_par_": 
                                    {
                                      "_logsigma_sq_": 7.306574e-02
                                    }
                              }
                            ]
                        },
                        {
                          "__family__": "normal",
                          "__name__": "E_4",
                          "__type__": "expert",
                          "_beta_": 
                              [ 2.653984e-03, -2.218735e-03 ],
                          "_par_": 
                              {
                                "_logsigma_sq_": 1.591248e-01
                              }
                        }
                      ]
                  }
                ]
            }
          ]
      }
    ]
},{
  "__name__": "G_1",
  "__type__": "gate",
  "_gamma_": 
      [ [ -4.624155e+00 ],
        [ 2.318403e+00 ] ],
  "children": 
    [
      {
        "__family__": "normal",
        "__name__": "E_1",
        "__type__": "expert",
        "_beta_": 
            [ -6.764655e-03, -4.842684e-05 ],
        "_par_": 
            {
              "_logsigma_sq_": 1.328509e+00
            }
      },
      {
        "__name__": "G_2",
        "__type__": "gate",
        "_gamma_": 
            [ [ -7.157646e-01 ],
              [ 1.049860e+00 ] ],
        "children": 
          [
            {
              "__family__": "normal",
              "__name__": "E_2",
              "__type__": "expert",
              "_beta_": 
                  [ 5.879902e-03, 4.763090e-03 ],
              "_par_": 
                  {
                    "_logsigma_sq_": 5.048653e+00
                  }
            },
            {
              "__name__": "G_3",
              "__type__": "gate",
              "_gamma_": 
                  [ [ -1.402009e+00 ],
                    [ 3.159036e+00 ] ],
              "children": 
                [
                  {
                    "__family__": "normal",
                    "__name__": "E_3",
                    "__type__": "expert",
                    "_beta_": 
                        [ -8.941114e-04, 1.151182e-02 ],
                    "_par_": 
                        {
                          "_logsigma_sq_": 1.966504e-01
                        }
                  },
                  {
                    "__name__": "G_4",
                    "__type__": "gate",
                    "_gamma_": 
                        [ [ 2.315619e+00 ],
                          [ -9.053089e-01 ] ],
                    "children": 
                      [
                        {
                          "__name__": "G_5",
                          "__type__": "gate",
                          "_gamma_": 
                              [ [ 2.888717e+01 ],
                                [ -2.923115e+01 ] ],
                          "children": 
                            [
                              {
                                "__family__": "normal",
                                "__name__": "E_5",
                                "__type__": "expert",
                                "_beta_": 
                                    [ 3.568495e-03, 1.271796e-02 ],
                                "_par_": 
                                    {
                                      "_logsigma_sq_": 5.038267e-02
                                    }
                              },
                              {
                                "__family__": "normal",
                                "__name__": "E_6",
                                "__type__": "expert",
                                "_beta_": 
                                    [ 2.873055e-03, 8.572967e-03 ],
                                "_par_": 
                                    {
                                      "_logsigma_sq_": 2.936298e-01
                                    }
                              }
                            ]
                        },
                        {
                          "__family__": "normal",
                          "__name__": "E_4",
                          "__type__": "expert",
                          "_beta_": 
                              [ 2.618174e-03, 8.205609e-06 ],
                          "_par_": 
                              {
                                "_logsigma_sq_": 1.050719e+00
                              }
                        }
                      ]
                  }
                ]
            }
          ]
      }
    ]
},{
  "__name__": "G_1",
  "__type__": "gate",
  "_gamma_": 
      [ [ -4.624155e+00 ],
        [ 2.318403e+00 ] ],
  "children": 
    [
      {
        "__family__": "normal",
        "__name__": "E_1",
        "__type__": "expert",
        "_beta_": 
            [ -2.275086e-03, -1.505789e-03 ],
        "_par_": 
            {
              "_logsigma_sq_": 3.122379e-01
            }
      },
      {
        "__name__": "G_2",
        "__type__": "gate",
        "_gamma_": 
            [ [ -3.244071e-02 ],
              [ 3.545977e-02 ] ],
        "children": 
          [
            {
              "__family__": "normal",
              "__name__": "E_2",
              "__type__": "expert",
              "_beta_": 
                  [ -2.710594e-03, 1.883267e-03 ],
              "_par_": 
                  {
                    "_logsigma_sq_": 5.782558e-02
                  }
            },
            {
              "__name__": "G_3",
              "__type__": "gate",
              "_gamma_": 
                  [ [ -3.572791e+00 ],
                    [ 7.959848e-01 ] ],
              "children": 
                [
                  {
                    "__family__": "normal",
                    "__name__": "E_3",
                    "__type__": "expert",
                    "_beta_": 
                        [ 1.344076e-03, -2.787174e-03 ],
                    "_par_": 
                        {
                          "_logsigma_sq_": 1.890596e+00
                        }
                  },
                  {
                    "__name__": "G_4",
                    "__type__": "gate",
                    "_gamma_": 
                        [ [ 7.304923e-01 ],
                          [ -7.263736e-01 ] ],
                    "children": 
                      [
                        {
                          "__name__": "G_5",
                          "__type__": "gate",
                          "_gamma_": 
                              [ [ 2.888717e+01 ],
                                [ -2.923115e+01 ] ],
                          "children": 
                            [
                              {
                                "__family__": "normal",
                                "__name__": "E_5",
                                "__type__": "expert",
                                "_beta_": 
                                    [ -4.655025e-03, 2.165476e-03 ],
                                "_par_": 
                                    {
                                      "_logsigma_sq_": 1.586717e-01
                                    }
                              },
                              {
                                "__family__": "normal",
                                "__name__": "E_6",
                                "__type__": "expert",
                                "_beta_": 
                                    [ -6.076871e-03, 1.574769e-02 ],
                                "_par_": 
                                    {
                                      "_logsigma_sq_": 6.614474e-01
                                    }
                              }
                            ]
                        },
                        {
                          "__family__": "normal",
                          "__name__": "E_4",
                          "__type__": "expert",
                          "_beta_": 
                              [ 8.420857e-04, -9.425404e-04 ],
                          "_par_": 
                              {
                                "_logsigma_sq_": 1.780859e-01
                              }
                        }
                      ]
                  }
                ]
            }
          ]
      }
    ]
},{
  "__name__": "G_1",
  "__type__": "gate",
  "_gamma_": 
      [ [ -4.624155e+00 ],
        [ 2.318403e+00 ] ],
  "children": 
    [
      {
        "__family__": "normal",
        "__name__": "E_1",
        "__type__": "expert",
        "_beta_": 
            [ -6.760292e-03, -5.095601e-03 ],
        "_par_": 
            {
              "_logsigma_sq_": 3.772775e-01
            }
      },
      {
        "__name__": "G_2",
        "__type__": "gate",
        "_gamma_": 
            [ [ -3.244071e-02 ],
              [ 3.545977e-02 ] ],
        "children": 
          [
            {
              "__family__": "normal",
              "__name__": "E_2",
              "__type__": "expert",
              "_beta_": 
                  [ 1.066592e-02, 1.299580e-02 ],
              "_par_": 
                  {
                    "_logsigma_sq_": 3.451374e-01
                  }
            },
            {
              "__name__": "G_3",
              "__type__": "gate",
              "_gamma_": 
                  [ [ -3.572791e+00 ],
                    [ 7.959848e-01 ] ],
              "children": 
                [
                  {
                    "__family__": "normal",
                    "__name__": "E_3",
                    "__type__": "expert",
                    "_beta_": 
                        [ -1.549590e-02, -8.518972e-03 ],
                    "_par_": 
                        {
                          "_logsigma_sq_": 1.006982e-01
                        }
                  },
                  {
                    "__name__": "G_4",
                    "__type__": "gate",
                    "_gamma_": 
                        [ [ 7.304923e-01 ],
                          [ -7.263736e-01 ] ],
                    "children": 
                      [
                        {
                          "__name__": "G_5",
                          "__type__": "gate",
                          "_gamma_": 
                              [ [ 2.888717e+01 ],
                                [ -2.923115e+01 ] ],
                          "children": 
                            [
                              {
                                "__family__": "normal",
                                "__name__": "E_5",
                                "__type__": "expert",
                                "_beta_": 
                                    [ -3.300804e-04, 1.612809e-03 ],
                                "_par_": 
                                    {
                                      "_logsigma_sq_": 7.942410e-01
                                    }
                              },
                              {
                                "__family__": "normal",
                                "__name__": "E_6",
                                "__type__": "expert",
                                "_beta_": 
                                    [ -3.450096e-03, -3.497495e-03 ],
                                "_par_": 
                                    {
                                      "_logsigma_sq_": 7.426272e-02
                                    }
                              }
                            ]
                        },
                        {
                          "__family__": "normal",
                          "__name__": "E_4",
                          "__type__": "expert",
                          "_beta_": 
                              [ 6.790387e-04, 8.970956e-03 ],
                          "_par_": 
                              {
                                "_logsigma_sq_": 2.361231e+00
                              }
                        }
                      ]
                  }
                ]
            }
          ]
      }
    ]
},{
  "__name__": "G_1",
  "__type__": "gate",
  "_gamma_": 
      [ [ -4.624155e+00 ],
        [ 2.318403e+00 ] ],
  "children": 
    [
      {
        "__family__": "normal",
        "__name__": "E_1",
        "__type__": "expert",
        "_beta_": 
            [ -5.680103e-03, -5.510990e-03 ],
        "_par_": 
            {
              "_logsigma_sq_": 9.856891e-02
            }
      },
      {
        "__name__": "G_2",
        "__type__": "gate",
        "_gamma_": 
            [ [ 1.448307e+00 ],
              [ -2.688247e+00 ] ],
        "children": 
          [
            {
              "__family__": "normal",
              "__name__": "E_2",
              "__type__": "expert",
              "_beta_": 
                  [ -3.582977e-03, 6.513632e-03 ],
              "_par_": 
                  {
                    "_logsigma_sq_": 6.561174e-01
                  }
            },
            {
              "__name__": "G_3",
              "__type__": "gate",
              "_gamma_": 
                  [ [ -3.572791e+00 ],
                    [ 7.959848e-01 ] ],
              "children": 
                [
                  {
                    "__family__": "normal",
                    "__name__": "E_3",
                    "__type__": "expert",
                    "_beta_": 
                        [ 4.925839e-03, 4.818739e-03 ],
                    "_par_": 
                        {
                          "_logsigma_sq_": 2.586767e-01
                        }
                  },
                  {
                    "__name__": "G_4",
                    "__type__": "gate",
                    "_gamma_": 
                        [ [ 2.229462e+00 ],
                          [ -1.217979e+00 ] ],
                    "children": 
                      [
                        {
                          "__name__": "G_5",
                          "__type__": "gate",
                          "_gamma_": 
                              [ [ 8.982798e+00 ],
                                [ 2.609109e+01 ] ],
                          "children": 
                            [
                              {
                                "__family__": "normal",
                                "__name__": "E_5",
                                "__type__": "expert",
                                "_beta_": 
                                    [ 2.443961e-03, -1.520125e-03 ],
                                "_par_": 
                                    {
                                      "_logsigma_sq_": 2.862703e-01
                                    }
                              },
                              {
                                "__family__": "normal",
                                "__name__": "E_6",
                                "__type__": "expert",
                                "_beta_": 
                                    [ -2.512333e-04, -2.281802e-03 ],
                                "_par_": 
                                    {
                                      "_logsigma_sq_": 6.726720e-02
                                    }
                              }
                            ]
                        },
                        {
                          "__family__": "normal",
                          "__name__": "E_4",
                          "__type__": "expert",
                          "_beta_": 
                              [ -2.275224e-03, -5.790930e-03 ],
                          "_par_": 
                              {
                                "_logsigma_sq_": 3.455904e-01
                              }
                        }
                      ]
                  }
                ]
            }
          ]
      }
    ]
},{
  "__name__": "G_1",
  "__type__": "gate",
  "_gamma_": 
      [ [ -4.624155e+00 ],
        [ 2.318403e+00 ] ],
  "children": 
    [
      {
        "__family__": "normal",
        "__name__": "E_1",
        "__type__": "expert",
        "_beta_": 
            [ -5.082920e-03, 4.382997e-03 ],
        "_par_": 
            {
              "_logsigma_sq_": 1.133983e+00
            }
      },
      {
        "__name__": "G_2",
        "__type__": "gate",
        "_gamma_": 
            [ [ -7.728583e-01 ],
              [ -1.186873e+00 ] ],
        "children": 
          [
            {
              "__family__": "normal",
              "__name__": "E_2",
              "__type__": "expert",
              "_beta_": 
                  [ 1.358582e-02, -2.411992e-04 ],
              "_par_": 
                  {
                    "_logsigma_sq_": 3.415622e-01
                  }
            },
            {
              "__name__": "G_3",
              "__type__": "gate",
              "_gamma_": 
                  [ [ 4.507382e+00 ],
                    [ 2.887862e+01 ] ],
              "children": 
                [
                  {
                    "__family__": "normal",
                    "__name__": "E_3",
                    "__type__": "expert",
                    "_beta_": 
                        [ -4.558200e-03, -1.195737e-03 ],
                    "_par_": 
                        {
                          "_logsigma_sq_": 4.006211e-01
                        }
                  },
                  {
                    "__name__": "G_4",
                    "__type__": "gate",
                    "_gamma_": 
                        [ [ -1.762637e+00 ],
                          [ -7.528037e-01 ] ],
                    "children": 
                      [
                        {
                          "__name__": "G_5",
                          "__type__": "gate",
                          "_gamma_": 
                              [ [ -3.989868e+00 ],
                                [ -2.695104e+01 ] ],
                          "children": 
                            [
                              {
                                "__family__": "normal",
                                "__name__": "E_5",
                                "__type__": "expert",
                                "_beta_": 
                                    [ 3.853451e-03, 2.013598e-03 ],
                                "_par_": 
                                    {
                                      "_logsigma_sq_": 5.407828e-01
                                    }
                              },
                              {
                                "__family__": "normal",
                                "__name__": "E_6",
                                "__type__": "expert",
                                "_beta_": 
                                    [ 2.642476e-03, 7.744300e-03 ],
                                "_par_": 
                                    {
                                      "_logsigma_sq_": 1.398291e-01
                                    }
                              }
                            ]
                        },
                        {
                          "__family__": "normal",
                          "__name__": "E_4",
                          "__type__": "expert",
                          "_beta_": 
                              [ 1.403482e-05, -2.400498e-03 ],
                          "_par_": 
                              {
                                "_logsigma_sq_": 4.837757e-02
                              }
                        }
                      ]
                  }
                ]
            }
          ]
      }
    ]
},]
